{"Agent 1": {"Agencies No": {"Jan-17": 75, "Feb-17": 1, "Mar-17": 1}, "Customer No": {"Jan-17": 51, "Feb-17": 137, "Mar-17": 129}, "New Customer No": {"Jan-17": 52, "Feb-17": 1, "Mar-17": 5}, "Paid Up No": {"Jan-17": 53, "Feb-17": 3, "Mar-17": 6}, "Sales No": {"Jan-17": 54, "Feb-17": 0, "Mar-17": 0}, "Sales Value": {"Jan-17": 55, "Feb-17": 0, "Mar-17": 0}, "Parallel No": {"Jan-17": 56, "Feb-17": 0, "Mar-17": 0}, "Refinance No": {"Jan-17": 57, "Feb-17": 0, "Mar-17": 0}, "Real Misses No": {"Jan-17": 58, "Feb-17": 35, "Mar-17": 27}, "Recent New Customers No 13 Weeks": {"Jan-17": 59, "Feb-17": 55, "Mar-17": 42}, "Consecutive Misses 1": {"Jan-17": 60, "Feb-17": 11, "Mar-17": 5}, "Scheduled Visit No": {"Jan-17": 61, "Feb-17": 6, "Mar-17": 5}}, "Agent 2": {"Agencies No": {"Jan-17": 62, "Feb-17": 1, "Mar-17": 1}, "Customer No": {"Jan-17": 63, "Feb-17": 286, "Mar-17": 260}, "New Customer No": {"Jan-17": 64, "Feb-17": 3, "Mar-17": 3}, "Paid Up No": {"Jan-17": 65, "Feb-17": 9, "Mar-17": 12}, "Sales No": {"Jan-17": 66, "Feb-17": 0, "Mar-17": 1}, "Sales Value": {"Jan-17": 67, "Feb-17": 0, "Mar-17": 13771}, "Parallel No": {"Jan-17": 68, "Feb-17": 0, "Mar-17": 0}, "Refinance No": {"Jan-17": 69, "Feb-17": 0, "Mar-17": 0}, "Real Misses No": {"Jan-17": 70, "Feb-17": 121, "Mar-17": 128}, "Recent New Customers No 13 Weeks": {"Jan-17": 71, "Feb-17": 77, "Mar-17": 67}, "Consecutive Misses 1": {"Jan-17": 72, "Feb-17": 38, "Mar-17": 39}, "Scheduled Visit No": {"Jan-17": 73, "Feb-17": 34, "Mar-17": 16}}, "Agent 3": {"Agencies No": {"Jan-17": 74, "Feb-17": 1, "Mar-17": 1}, "Customer No": {"Jan-17": 75, "Feb-17": 131, "Mar-17": 113}, "New Customer No": {"Jan-17": 76, "Feb-17": 0, "Mar-17": 4}, "Paid Up No": {"Jan-17": 77, "Feb-17": 2, "Mar-17": 4}, "Sales No": {"Jan-17": 78, "Feb-17": 0, "Mar-17": 5}, "Sales Value": {"Jan-17": 79, "Feb-17": 0, "Mar-17": 8124}, "Parallel No": {"Jan-17": 80, "Feb-17": 0, "Mar-17": 0}, "Refinance No": {"Jan-17": 81, "Feb-17": 0, "Mar-17": 0}, "Real Misses No": {"Jan-17": 82, "Feb-17": 46, "Mar-17": 27}, "Recent New Customers No 13 Weeks": {"Jan-17": 83, "Feb-17": 24, "Mar-17": 13}, "Consecutive Misses 1": {"Jan-17": 84, "Feb-17": 21, "Mar-17": 8}, "Scheduled Visit No": {"Jan-17": 85, "Feb-17": 12, "Mar-17": 4}}, "Agent 4": {"Agencies No": {"Jan-17": 86, "Feb-17": "", "Mar-17": ""}, "Customer No": {"Jan-17": 87, "Feb-17": "", "Mar-17": ""}, "New Customer No": {"Jan-17": 88, "Feb-17": "", "Mar-17": ""}, "Paid Up No": {"Jan-17": 89, "Feb-17": "", "Mar-17": ""}, "Sales No": {"Jan-17": 90, "Feb-17": "", "Mar-17": ""}, "Sales Value": {"Jan-17": 91, "Feb-17": "", "Mar-17": ""}, "Parallel No": {"Jan-17": 92, "Feb-17": "", "Mar-17": ""}, "Refinance No": {"Jan-17": 93, "Feb-17": "", "Mar-17": ""}, "Real Misses No": {"Jan-17": 94, "Feb-17": "", "Mar-17": ""}, "Recent New Customers No 13 Weeks": {"Jan-17": 95, "Feb-17": "", "Mar-17": ""}, "Consecutive Misses 1": {"Jan-17": 96, "Feb-17": "", "Mar-17": ""}, "Scheduled Visit No": {"Jan-17": 97, "Feb-17": "", "Mar-17": ""}}, "Agent 5": {"Agencies No": {"Jan-17": 98, "Feb-17": 1, "Mar-17": 1}, "Customer No": {"Jan-17": 99, "Feb-17": 221, "Mar-17": 212}, "New Customer No": {"Jan-17": 100, "Feb-17": 1, "Mar-17": 7}, "Paid Up No": {"Jan-17": 101, "Feb-17": 4, "Mar-17": 8}, "Sales No": {"Jan-17": 102, "Feb-17": 0, "Mar-17": 2}, "Sales Value": {"Jan-17": 103, "Feb-17": 0, "Mar-17": 12247}, "Parallel No": {"Jan-17": 104, "Feb-17": 0, "Mar-17": 0}, "Refinance No": {"Jan-17": 105, "Feb-17": 0, "Mar-17": 0}, "Real Misses No": {"Jan-17": 106, "Feb-17": 77, "Mar-17": 100}, "Recent New Customers No 13 Weeks": {"Jan-17": 107, "Feb-17": 72, "Mar-17": 72}, "Consecutive Misses 1": {"Jan-17": 108, "Feb-17": 33, "Mar-17": 23}, "Scheduled Visit No": {"Jan-17": 109, "Feb-17": 26, "Mar-17": 23}}, "Agent 6": {"Agencies No": {"Jan-17": 110, "Feb-17": 1, "Mar-17": 1}, "Customer No": {"Jan-17": 111, "Feb-17": 310, "Mar-17": 288}, "New Customer No": {"Jan-17": 112, "Feb-17": 3, "Mar-17": 3}, "Paid Up No": {"Jan-17": 113, "Feb-17": 6, "Mar-17": 9}, "Sales No": {"Jan-17": 114, "Feb-17": 0, "Mar-17": 1}, "Sales Value": {"Jan-17": 115, "Feb-17": 0, "Mar-17": 4976}, "Parallel No": {"Jan-17": 116, "Feb-17": 0, "Mar-17": 0}, "Refinance No": {"Jan-17": 117, "Feb-17": 0, "Mar-17": 0}, "Real Misses No": {"Jan-17": 118, "Feb-17": 82, "Mar-17": 107}, "Recent New Customers No 13 Weeks": {"Jan-17": 119, "Feb-17": 97, "Mar-17": 61}, "Consecutive Misses 1": {"Jan-17": 120, "Feb-17": 34, "Mar-17": 24}, "Scheduled Visit No": {"Jan-17": 121, "Feb-17": 28, "Mar-17": 19}}, "Agent 7": {"Agencies No": {"Jan-17": 122, "Feb-17": "", "Mar-17": ""}, "Customer No": {"Jan-17": 123, "Feb-17": 0, "Mar-17": 0}, "New Customer No": {"Jan-17": 124, "Feb-17": 0, "Mar-17": 0}, "Paid Up No": {"Jan-17": 125, "Feb-17": 0, "Mar-17": 0}, "Sales No": {"Jan-17": 126, "Feb-17": 0, "Mar-17": 0}, "Sales Value": {"Jan-17": 127, "Feb-17": 0, "Mar-17": 0}, "Parallel No": {"Jan-17": 128, "Feb-17": 0, "Mar-17": 0}, "Refinance No": {"Jan-17": 129, "Feb-17": 0, "Mar-17": 0}, "Real Misses No": {"Jan-17": 130, "Feb-17": 0, "Mar-17": 0}, "Recent New Customers No 13 Weeks": {"Jan-17": 131, "Feb-17": 0, "Mar-17": 0}, "Consecutive Misses 1": {"Jan-17": 132, "Feb-17": 0, "Mar-17": 0}, "Scheduled Visit No": {"Jan-17": 133, "Feb-17": "", "Mar-17": ""}}, "Agent 8": {"Agencies No": {"Jan-17": 134, "Feb-17": 1, "Mar-17": 1}, "Customer No": {"Jan-17": 135, "Feb-17": 363, "Mar-17": 326}, "New Customer No": {"Jan-17": 136, "Feb-17": 3, "Mar-17": 3}, "Paid Up No": {"Jan-17": 137, "Feb-17": 5, "Mar-17": 27}, "Sales No": {"Jan-17": 138, "Feb-17": 0, "Mar-17": 5}, "Sales Value": {"Jan-17": 139, "Feb-17": 0, "Mar-17": 20950}, "Parallel No": {"Jan-17": 140, "Feb-17": 0, "Mar-17": 0}, "Refinance No": {"Jan-17": 141, "Feb-17": 0, "Mar-17": 0}, "Real Misses No": {"Jan-17": 142, "Feb-17": 114, "Mar-17": 111}, "Recent New Customers No 13 Weeks": {"Jan-17": 143, "Feb-17": 111, "Mar-17": 55}, "Consecutive Misses 1": {"Jan-17": 144, "Feb-17": 33, "Mar-17": 20}, "Scheduled Visit No": {"Jan-17": 145, "Feb-17": 29, "Mar-17": 20}}, "Agent 9": {"Agencies No": {"Jan-17": 146, "Feb-17": 1, "Mar-17": 1}, "Customer No": {"Jan-17": 147, "Feb-17": 213, "Mar-17": 203}, "New Customer No": {"Jan-17": 148, "Feb-17": 1, "Mar-17": 8}, "Paid Up No": {"Jan-17": 149, "Feb-17": 10, "Mar-17": 11}, "Sales No": {"Jan-17": 150, "Feb-17": 3, "Mar-17": 3}, "Sales Value": {"Jan-17": 151, "Feb-17": 11865, "Mar-17": 21187}, "Parallel No": {"Jan-17": 152, "Feb-17": 0, "Mar-17": 0}, "Refinance No": {"Jan-17": 153, "Feb-17": 0, "Mar-17": 0}, "Real Misses No": {"Jan-17": 154, "Feb-17": 79, "Mar-17": 64}, "Recent New Customers No 13 Weeks": {"Jan-17": 155, "Feb-17": 28, "Mar-17": 59}, "Consecutive Misses 1": {"Jan-17": 156, "Feb-17": 28, "Mar-17": 18}, "Scheduled Visit No": {"Jan-17": 157, "Feb-17": 15, "Mar-17": 11}}, "Agent 10": {"Agencies No": {"Jan-17": 158, "Feb-17": 1, "Mar-17": ""}, "Customer No": {"Jan-17": 159, "Feb-17": 88, "Mar-17": 0}, "New Customer No": {"Jan-17": 160, "Feb-17": 1, "Mar-17": 0}, "Paid Up No": {"Jan-17": 161, "Feb-17": 1, "Mar-17": 4}, "Sales No": {"Jan-17": 162, "Feb-17": 1, "Mar-17": 0}, "Sales Value": {"Jan-17": 163, "Feb-17": 1182, "Mar-17": 0}, "Parallel No": {"Jan-17": 164, "Feb-17": 0, "Mar-17": 0}, "Refinance No": {"Jan-17": 165, "Feb-17": 0, "Mar-17": 0}, "Real Misses No": {"Jan-17": 166, "Feb-17": 47, "Mar-17": 0}, "Recent New Customers No 13 Weeks": {"Jan-17": 167, "Feb-17": 28, "Mar-17": 5}, "Consecutive Misses 1": {"Jan-17": 168, "Feb-17": 16, "Mar-17": 0}, "Scheduled Visit No": {"Jan-17": 169, "Feb-17": 5, "Mar-17": 0}}, "Agent 11": {"Agencies No": {"Jan-17": 170, "Feb-17": 1, "Mar-17": 1}, "Customer No": {"Jan-17": 171, "Feb-17": 248, "Mar-17": 142}, "New Customer No": {"Jan-17": 172, "Feb-17": 3, "Mar-17": 0}, "Paid Up No": {"Jan-17": 173, "Feb-17": 1, "Mar-17": 9}, "Sales No": {"Jan-17": 174, "Feb-17": 4, "Mar-17": 6}, "Sales Value": {"Jan-17": 175, "Feb-17": 2815, "Mar-17": 5786}, "Parallel No": {"Jan-17": 176, "Feb-17": 0, "Mar-17": 0}, "Refinance No": {"Jan-17": 177, "Feb-17": 0, "Mar-17": 0}, "Real Misses No": {"Jan-17": 178, "Feb-17": 128, "Mar-17": 59}, "Recent New Customers No 13 Weeks": {"Jan-17": 179, "Feb-17": 60, "Mar-17": 31}, "Consecutive Misses 1": {"Jan-17": 180, "Feb-17": 29, "Mar-17": 14}, "Scheduled Visit No": {"Jan-17": 181, "Feb-17": 21, "Mar-17": 17}}, "Agent 12": {"Agencies No": {"Jan-17": 182, "Feb-17": 1, "Mar-17": 1}, "Customer No": {"Jan-17": 183, "Feb-17": 233, "Mar-17": 172}, "New Customer No": {"Jan-17": 184, "Feb-17": 2, "Mar-17": 0}, "Paid Up No": {"Jan-17": 185, "Feb-17": 4, "Mar-17": 9}, "Sales No": {"Jan-17": 186, "Feb-17": 8, "Mar-17": 1}, "Sales Value": {"Jan-17": 187, "Feb-17": 11687, "Mar-17": 679}, "Parallel No": {"Jan-17": 188, "Feb-17": 0, "Mar-17": 0}, "Refinance No": {"Jan-17": 189, "Feb-17": 0, "Mar-17": 0}, "Real Misses No": {"Jan-17": 190, "Feb-17": 96, "Mar-17": 78}, "Recent New Customers No 13 Weeks": {"Jan-17": 191, "Feb-17": 23, "Mar-17": 13}, "Consecutive Misses 1": {"Jan-17": 192, "Feb-17": 39, "Mar-17": 27}, "Scheduled Visit No": {"Jan-17": 193, "Feb-17": 21, "Mar-17": 17}}, "Agent 13": {"Agencies No": {"Jan-17": 194, "Feb-17": 1, "Mar-17": 1}, "Customer No": {"Jan-17": 195, "Feb-17": 167, "Mar-17": 136}, "New Customer No": {"Jan-17": 196, "Feb-17": 3, "Mar-17": 1}, "Paid Up No": {"Jan-17": 197, "Feb-17": 3, "Mar-17": 4}, "Sales No": {"Jan-17": 198, "Feb-17": 8, "Mar-17": 2}, "Sales Value": {"Jan-17": 199, "Feb-17": 14103, "Mar-17": 3468}, "Parallel No": {"Jan-17": 200, "Feb-17": 0, "Mar-17": 0}, "Refinance No": {"Jan-17": 201, "Feb-17": 0, "Mar-17": 0}, "Real Misses No": {"Jan-17": 202, "Feb-17": 83, "Mar-17": 49}, "Recent New Customers No 13 Weeks": {"Jan-17": 203, "Feb-17": 67, "Mar-17": 40}, "Consecutive Misses 1": {"Jan-17": 204, "Feb-17": 40, "Mar-17": 12}, "Scheduled Visit No": {"Jan-17": 205, "Feb-17": 25, "Mar-17": 18}}, "Lead Agent": {"Agencies No": {"Jan-17": 206, "Feb-17": 11, "Mar-17": 10}, "Customer No": {"Jan-17": 207, "Feb-17": 2403, "Mar-17": 1986}, "New Customer No": {"Jan-17": 208, "Feb-17": 25, "Mar-17": 36}, "Paid Up No": {"Jan-17": 209, "Feb-17": 52, "Mar-17": 109}, "Sales No": {"Jan-17": 210, "Feb-17": 25, "Mar-17": 30}, "Sales Value": {"Jan-17": 211, "Feb-17": 41653, "Mar-17": 91190}, "Parallel No": {"Jan-17": 212, "Feb-17": 0, "Mar-17": 0}, "Refinance No": {"Jan-17": 213, "Feb-17": 0, "Mar-17": 0}, "Real Misses No": {"Jan-17": 214, "Feb-17": 912, "Mar-17": 755}, "Recent New Customers No 13 Weeks": {"Jan-17": 215, "Feb-17": 647, "Mar-17": 463}, "Consecutive Misses 1": {"Jan-17": 216, "Feb-17": 327, "Mar-17": 194}, "Scheduled Visit No": {"Jan-17": 217, "Feb-17": 227, "Mar-17": 154}}}